dooku-0.3.0.dist-info/METADATA
dooku-0.3.0.dist-info/top_level.txt
dooku-0.3.0.dist-info/WHEEL
dooku-0.3.0.dist-info/RECORD
dooku-0.3.0.dist-info/DESCRIPTION.rst
dooku-0.3.0.dist-info/metadata.json
dooku/datetime.py
dooku/ext.py
dooku/conf.py
dooku/algorithm.py
dooku/decorator.py
dooku/__init__.py
