Metadata-Version: 2.0
Name: dooku
Version: 0.3.0
Summary: a set of libraries for everyday
Home-page: https://github.com/ikalnitsky/dooku
Author: Igor Kalnitsky
Author-email: igor@kalnitsky.org
License: BSD
Platform: any
Classifier: Intended Audience :: Developers
Classifier: License :: OSI Approved :: BSD License
Classifier: Programming Language :: Python
Classifier: Programming Language :: Python :: 3
Classifier: Programming Language :: Python :: 3.2
Classifier: Programming Language :: Python :: 3.3
Classifier: Programming Language :: Python :: 3.4
Classifier: Programming Language :: Python :: Implementation :: CPython
Classifier: Programming Language :: Python :: Implementation :: PyPy
Classifier: Topic :: Software Development :: Libraries
Classifier: Topic :: Utilities
